lektor_redirect-0.1.0b2.dist-info/METADATA
lektor_redirect-0.1.0b2.dist-info/WHEEL
lektor_redirect-0.1.0b2.dist-info/entry_points.txt
lektor_redirect-0.1.0b2.dist-info/licenses/LICENSE
lektor_redirect/__init__.py
lektor_redirect/exceptions.py
lektor_redirect/plugin.py
lektor_redirect/py.typed
lektor_redirect/sources.py
lektor_redirect/util.py
lektor_redirect-0.1.0b2.dist-info/RECORD
