Metadata-Version: 2.1
Name: lektor-redirect
Version: 0.1.0b2
Summary: A Lektor plugin to help with generating redirects for, e.g., moved pages.
Keywords: lektor,plugin
Author-Email: Jeff Dairiki <dairiki@dairiki.org>
License: MIT
Classifier: Development Status :: 4 - Beta
Classifier: Environment :: Plugins
Classifier: Environment :: Web Environment
Classifier: Framework :: Lektor
Classifier: Intended Audience :: Developers
Classifier: License :: OSI Approved :: MIT License
Classifier: Programming Language :: Python :: 3
Classifier: Programming Language :: Python :: 3.8
Classifier: Programming Language :: Python :: 3.9
Classifier: Programming Language :: Python :: 3.10
Classifier: Programming Language :: Python :: 3.11
Classifier: Programming Language :: Python :: 3.12
Classifier: Topic :: Text Processing
Project-URL: Home, https://github.com/dairiki/lektor-redirect
Requires-Python: >=3.8
Requires-Dist: lektorlib>=1.2.1
Requires-Dist: typing-extensions>=4.12.2; python_version < "3.11"
